smtp4helm/__init__.py
smtp4helm/mail.py
smtp4helm-0.0.2.dist-info/LICENSE
smtp4helm-0.0.2.dist-info/METADATA
smtp4helm-0.0.2.dist-info/WHEEL
smtp4helm-0.0.2.dist-info/top_level.txt
smtp4helm-0.0.2.dist-info/RECORD
